{
  "version": "1.0",
  "countryIso": "AE",
  "countryName": "United Arab Emirates",
  "catalogType": "imaging-studies",
  "entries": [
    {
      "studyName": "Chest X-Ray 2 Views",
      "cptCode": "71046",
      "localCode": "IMG-001",
      "modality": "X-ray",
      "bodyPart": "Chest",
      "studyCategory": "Radiography",
      "contrastRequired": false,
      "contrastType": null,
      "preparationInstructions": "Remove all jewelry and metallic objects from the chest area. Wear a hospital gown.",
      "positioningInstructions": "PA (posteroanterior) and lateral views. Patient standing upright, deep inspiration.",
      "contraindications": [
        "Pregnancy (relative - shield abdomen if necessary)"
      ],
      "radiationDose": "0.1 mSv",
      "estimatedDurationMinutes": 10,
      "facilityRequirements": "Radiology suite with X-ray equipment",
      "equipmentRequirements": "Digital radiography system",
      "radiologistRequired": true
    },
    {
      "studyName": "Chest X-Ray Single View",
      "cptCode": "71045",
      "localCode": "IMG-002",
      "modality": "X-ray",
      "bodyPart": "Chest",
      "studyCategory": "Radiography",
      "contrastRequired": false,
      "contrastType": null,
      "preparationInstructions": "Remove all jewelry and metallic objects from the chest area. Wear a hospital gown.",
      "positioningInstructions": "PA (posteroanterior) view. Patient standing upright, deep inspiration.",
      "contraindications": [
        "Pregnancy (relative - shield abdomen if necessary)"
      ],
      "radiationDose": "0.05 mSv",
      "estimatedDurationMinutes": 5,
      "facilityRequirements": "Radiology suite with X-ray equipment",
      "equipmentRequirements": "Digital radiography system",
      "radiologistRequired": true
    },
    {
      "studyName": "Abdominal X-Ray (KUB)",
      "cptCode": "74018",
      "localCode": "IMG-003",
      "modality": "X-ray",
      "bodyPart": "Abdomen",
      "studyCategory": "Radiography",
      "contrastRequired": false,
      "contrastType": null,
      "preparationInstructions": "Remove belt, jewelry, and metallic objects. No bowel preparation typically required for standard KUB.",
      "positioningInstructions": "Supine AP view. Include kidneys, ureters, and bladder.",
      "contraindications": [
        "Pregnancy (relative - shield if necessary)"
      ],
      "radiationDose": "0.7 mSv",
      "estimatedDurationMinutes": 10,
      "facilityRequirements": "Radiology suite with X-ray equipment",
      "equipmentRequirements": "Digital radiography system",
      "radiologistRequired": true
    },
    {
      "studyName": "Hand X-Ray",
      "cptCode": "73130",
      "localCode": "IMG-004",
      "modality": "X-ray",
      "bodyPart": "Hand",
      "studyCategory": "Radiography",
      "contrastRequired": false,
      "contrastType": null,
      "preparationInstructions": "Remove rings, bracelets, and all jewelry from the hand and wrist.",
      "positioningInstructions": "PA, oblique, and lateral views. Hand flat on cassette, fingers spread.",
      "contraindications": [
        "Pregnancy (relative - shield abdomen)"
      ],
      "radiationDose": "0.001 mSv",
      "estimatedDurationMinutes": 10,
      "facilityRequirements": "Radiology suite with X-ray equipment",
      "equipmentRequirements": "Digital radiography system",
      "radiologistRequired": true
    },
    {
      "studyName": "CT Head without Contrast",
      "cptCode": "70450",
      "localCode": "IMG-005",
      "modality": "CT",
      "bodyPart": "Head",
      "studyCategory": "Computed Tomography",
      "contrastRequired": false,
      "contrastType": null,
      "preparationInstructions": "Remove all metallic objects from head and neck (earrings, hair clips, dentures). No fasting required.",
      "positioningInstructions": "Supine, head in head holder. Scan from skull base to vertex. Axial slices parallel to orbitomeatal line.",
      "contraindications": [
        "Pregnancy (relative)"
      ],
      "radiationDose": "2.0 mSv",
      "estimatedDurationMinutes": 10,
      "facilityRequirements": "CT suite",
      "equipmentRequirements": "Multi-detector CT scanner (minimum 16-slice)",
      "radiologistRequired": true
    },
    {
      "studyName": "CT Head with Contrast",
      "cptCode": "70460",
      "localCode": "IMG-006",
      "modality": "CT",
      "bodyPart": "Head",
      "studyCategory": "Computed Tomography",
      "contrastRequired": true,
      "contrastType": "Iodinated IV contrast",
      "preparationInstructions": "Check renal function (eGFR). NPO 4 hours prior. Assess for contrast allergy. Discontinue metformin if applicable.",
      "positioningInstructions": "Supine, head in head holder. Pre-contrast and post-contrast axial images from skull base to vertex.",
      "contraindications": [
        "Iodinated contrast allergy",
        "Severe renal impairment (eGFR < 30)",
        "Pregnancy",
        "Hyperthyroidism (relative)"
      ],
      "radiationDose": "2.0 mSv",
      "estimatedDurationMinutes": 20,
      "facilityRequirements": "CT suite with contrast injection capability",
      "equipmentRequirements": "Multi-detector CT scanner (minimum 16-slice), power injector",
      "radiologistRequired": true
    },
    {
      "studyName": "CT Abdomen and Pelvis with Contrast",
      "cptCode": "74177",
      "localCode": "IMG-007",
      "modality": "CT",
      "bodyPart": "Abdomen/Pelvis",
      "studyCategory": "Computed Tomography",
      "contrastRequired": true,
      "contrastType": "Iodinated IV contrast and/or oral contrast",
      "preparationInstructions": "NPO 4-6 hours prior. Oral contrast 1-2 hours before scan if ordered. Check renal function. Assess for contrast allergy. Hydrate well.",
      "positioningInstructions": "Supine, arms above head. Scan from diaphragm to pubic symphysis.",
      "contraindications": [
        "Iodinated contrast allergy",
        "Severe renal impairment (eGFR < 30)",
        "Pregnancy",
        "Metformin use (hold 48 hours post-contrast)"
      ],
      "radiationDose": "10.0 mSv",
      "estimatedDurationMinutes": 20,
      "facilityRequirements": "CT suite with contrast injection capability",
      "equipmentRequirements": "Multi-detector CT scanner (minimum 16-slice), power injector",
      "radiologistRequired": true
    },
    {
      "studyName": "CT Chest without Contrast",
      "cptCode": "71250",
      "localCode": "IMG-008",
      "modality": "CT",
      "bodyPart": "Chest",
      "studyCategory": "Computed Tomography",
      "contrastRequired": false,
      "contrastType": null,
      "preparationInstructions": "Remove all metallic objects from chest. Wear a hospital gown. Breath-hold instructions will be given.",
      "positioningInstructions": "Supine, arms above head. Scan from lung apices to adrenal glands. Full inspiration breath-hold.",
      "contraindications": [
        "Pregnancy (relative)"
      ],
      "radiationDose": "7.0 mSv",
      "estimatedDurationMinutes": 10,
      "facilityRequirements": "CT suite",
      "equipmentRequirements": "Multi-detector CT scanner (minimum 16-slice)",
      "radiologistRequired": true
    },
    {
      "studyName": "MRI Brain without Contrast",
      "cptCode": "70551",
      "localCode": "IMG-009",
      "modality": "MRI",
      "bodyPart": "Brain",
      "studyCategory": "Magnetic Resonance Imaging",
      "contrastRequired": false,
      "contrastType": null,
      "preparationInstructions": "Complete MRI safety screening questionnaire. Remove all metallic objects, jewelry, and electronic devices. No fasting required.",
      "positioningInstructions": "Supine, head in head coil. Axial, sagittal, and coronal sequences. T1, T2, FLAIR, DWI minimum.",
      "contraindications": [
        "Non-MRI-compatible cardiac pacemaker",
        "Ferromagnetic intracranial aneurysm clips",
        "Metallic foreign bodies (especially intraocular)",
        "Cochlear implants (non-MRI-compatible)",
        "Severe claustrophobia (relative)"
      ],
      "radiationDose": "0 mSv (no ionizing radiation)",
      "estimatedDurationMinutes": 30,
      "facilityRequirements": "MRI suite with appropriate shielding",
      "equipmentRequirements": "MRI scanner (minimum 1.5T, preferably 3T), head coil",
      "radiologistRequired": true
    },
    {
      "studyName": "MRI Brain with and without Contrast",
      "cptCode": "70553",
      "localCode": "IMG-010",
      "modality": "MRI",
      "bodyPart": "Brain",
      "studyCategory": "Magnetic Resonance Imaging",
      "contrastRequired": true,
      "contrastType": "Gadolinium-based IV contrast",
      "preparationInstructions": "Complete MRI safety screening questionnaire. Check renal function (risk of NSF with gadolinium). Remove all metallic objects. IV access required.",
      "positioningInstructions": "Supine, head in head coil. Pre- and post-contrast sequences. T1, T2, FLAIR, DWI, post-contrast T1 with fat saturation.",
      "contraindications": [
        "Non-MRI-compatible cardiac pacemaker",
        "Ferromagnetic intracranial aneurysm clips",
        "Severe renal impairment (risk of NSF with gadolinium)",
        "Gadolinium allergy",
        "Pregnancy (relative for contrast)",
        "Metallic foreign bodies"
      ],
      "radiationDose": "0 mSv (no ionizing radiation)",
      "estimatedDurationMinutes": 45,
      "facilityRequirements": "MRI suite with appropriate shielding, contrast injection capability",
      "equipmentRequirements": "MRI scanner (minimum 1.5T, preferably 3T), head coil, MRI-compatible power injector",
      "radiologistRequired": true
    },
    {
      "studyName": "MRI Lumbar Spine without Contrast",
      "cptCode": "72148",
      "localCode": "IMG-011",
      "modality": "MRI",
      "bodyPart": "Lumbar Spine",
      "studyCategory": "Magnetic Resonance Imaging",
      "contrastRequired": false,
      "contrastType": null,
      "preparationInstructions": "Complete MRI safety screening questionnaire. Remove all metallic objects. No fasting required.",
      "positioningInstructions": "Supine, spine coil. Sagittal and axial images through lumbar spine. T1, T2, STIR sequences.",
      "contraindications": [
        "Non-MRI-compatible cardiac pacemaker",
        "Ferromagnetic implants",
        "Metallic foreign bodies",
        "Severe claustrophobia (relative)"
      ],
      "radiationDose": "0 mSv (no ionizing radiation)",
      "estimatedDurationMinutes": 30,
      "facilityRequirements": "MRI suite with appropriate shielding",
      "equipmentRequirements": "MRI scanner (minimum 1.5T), spine coil",
      "radiologistRequired": true
    },
    {
      "studyName": "MRI Knee without Contrast",
      "cptCode": "73721",
      "localCode": "IMG-012",
      "modality": "MRI",
      "bodyPart": "Knee",
      "studyCategory": "Magnetic Resonance Imaging",
      "contrastRequired": false,
      "contrastType": null,
      "preparationInstructions": "Complete MRI safety screening questionnaire. Remove all metallic objects from the leg. No fasting required.",
      "positioningInstructions": "Supine, knee in dedicated knee coil. Sagittal, coronal, and axial images. PD, T2 FS, T1 sequences.",
      "contraindications": [
        "Non-MRI-compatible cardiac pacemaker",
        "Ferromagnetic implants near the knee",
        "Metallic foreign bodies",
        "Severe claustrophobia (relative)"
      ],
      "radiationDose": "0 mSv (no ionizing radiation)",
      "estimatedDurationMinutes": 30,
      "facilityRequirements": "MRI suite with appropriate shielding",
      "equipmentRequirements": "MRI scanner (minimum 1.5T), dedicated knee coil",
      "radiologistRequired": true
    },
    {
      "studyName": "Ultrasound Abdomen Complete",
      "cptCode": "76700",
      "localCode": "IMG-013",
      "modality": "Ultrasound",
      "bodyPart": "Abdomen",
      "studyCategory": "Ultrasonography",
      "contrastRequired": false,
      "contrastType": null,
      "preparationInstructions": "NPO (nothing by mouth) for 6-8 hours prior to examination. Water permitted. Full bladder preferred.",
      "positioningInstructions": "Supine and decubitus positions. Evaluate liver, gallbladder, bile ducts, pancreas, spleen, kidneys, and aorta.",
      "contraindications": [],
      "radiationDose": "0 mSv (no ionizing radiation)",
      "estimatedDurationMinutes": 30,
      "facilityRequirements": "Ultrasound examination room",
      "equipmentRequirements": "Ultrasound machine with curvilinear transducer (2-5 MHz)",
      "radiologistRequired": true
    },
    {
      "studyName": "Ultrasound Pelvis",
      "cptCode": "76856",
      "localCode": "IMG-014",
      "modality": "Ultrasound",
      "bodyPart": "Pelvis",
      "studyCategory": "Ultrasonography",
      "contrastRequired": false,
      "contrastType": null,
      "preparationInstructions": "Full bladder required for transabdominal approach. Drink 32 oz of water 1 hour prior. Do not void before exam.",
      "positioningInstructions": "Supine for transabdominal. Evaluate uterus, ovaries, adnexa, and bladder.",
      "contraindications": [],
      "radiationDose": "0 mSv (no ionizing radiation)",
      "estimatedDurationMinutes": 25,
      "facilityRequirements": "Ultrasound examination room",
      "equipmentRequirements": "Ultrasound machine with curvilinear (2-5 MHz) and endocavitary transducer (5-9 MHz)",
      "radiologistRequired": true
    },
    {
      "studyName": "Ultrasound Thyroid",
      "cptCode": "76536",
      "localCode": "IMG-015",
      "modality": "Ultrasound",
      "bodyPart": "Thyroid",
      "studyCategory": "Ultrasonography",
      "contrastRequired": false,
      "contrastType": null,
      "preparationInstructions": "No special preparation required. Remove necklaces and scarves.",
      "positioningInstructions": "Supine with neck slightly extended (pillow under shoulders). Evaluate both thyroid lobes, isthmus, and cervical lymph nodes.",
      "contraindications": [],
      "radiationDose": "0 mSv (no ionizing radiation)",
      "estimatedDurationMinutes": 20,
      "facilityRequirements": "Ultrasound examination room",
      "equipmentRequirements": "Ultrasound machine with high-frequency linear transducer (7-15 MHz)",
      "radiologistRequired": true
    },
    {
      "studyName": "Carotid Doppler Ultrasound",
      "cptCode": "93880",
      "localCode": "IMG-016",
      "modality": "Ultrasound",
      "bodyPart": "Carotid",
      "studyCategory": "Vascular Ultrasonography",
      "contrastRequired": false,
      "contrastType": null,
      "preparationInstructions": "No special preparation required. Remove necklaces.",
      "positioningInstructions": "Supine, head turned away from the side being examined. Evaluate bilateral common carotid, internal carotid, external carotid, and vertebral arteries.",
      "contraindications": [],
      "radiationDose": "0 mSv (no ionizing radiation)",
      "estimatedDurationMinutes": 30,
      "facilityRequirements": "Vascular ultrasound examination room",
      "equipmentRequirements": "Ultrasound machine with linear transducer (5-12 MHz) and Doppler capability",
      "radiologistRequired": true
    },
    {
      "studyName": "Mammogram Screening",
      "cptCode": "77067",
      "localCode": "IMG-017",
      "modality": "X-ray",
      "bodyPart": "Breast",
      "studyCategory": "Mammography",
      "contrastRequired": false,
      "contrastType": null,
      "preparationInstructions": "Do not apply deodorant, powder, or lotion under arms or on breasts on the day of the exam. Schedule preferably 1 week after menstruation.",
      "positioningInstructions": "Standing or seated. CC (craniocaudal) and MLO (mediolateral oblique) views of each breast.",
      "contraindications": [
        "Pregnancy",
        "Breast implant rupture (relative - notify technologist)"
      ],
      "radiationDose": "0.4 mSv",
      "estimatedDurationMinutes": 15,
      "facilityRequirements": "Mammography suite (ACR accredited preferred)",
      "equipmentRequirements": "Digital mammography unit (preferably with tomosynthesis capability)",
      "radiologistRequired": true
    },
    {
      "studyName": "Mammogram Diagnostic",
      "cptCode": "77066",
      "localCode": "IMG-018",
      "modality": "X-ray",
      "bodyPart": "Breast",
      "studyCategory": "Mammography",
      "contrastRequired": false,
      "contrastType": null,
      "preparationInstructions": "Do not apply deodorant, powder, or lotion under arms or on breasts on the day of the exam. Bring prior mammograms for comparison.",
      "positioningInstructions": "Standing or seated. CC and MLO views plus additional views as needed (spot compression, magnification, rolled views).",
      "contraindications": [
        "Pregnancy",
        "Breast implant rupture (relative - notify technologist)"
      ],
      "radiationDose": "0.4-0.7 mSv (varies with additional views)",
      "estimatedDurationMinutes": 30,
      "facilityRequirements": "Mammography suite (ACR accredited preferred)",
      "equipmentRequirements": "Digital mammography unit with spot compression and magnification capability",
      "radiologistRequired": true
    }
  ]
}
